full adder/full_adder.v
//Circuito meio somador de duas entradas: (1 bit)

module half_adder (a, b, s, c);
input a,b;
output s,c;

assign s = a ^ b;
assign c = a & b;

endmodule

//A partir do hal-adder que é possível criar um full adder

//Possui 3 entradas: a, b e um Carry In, que são somadas
//Duas saídas: S e Carry Out
//Novamente a soma é o resultado de um OU exclusivo
//Já o carry out vai ser um OU 

module full_adder (a, b, cin, soma, cout);

input a, b, cin;
output soma, cout;
wire carry1, carry2, soma1, soma2;


half_adder u1 (a, b, soma1,carry1);
half_adder u2 (cin, soma1, soma2, carry2);

assign soma = soma2;
assign cout = carry1 | carry2;

endmodule

//Injetar sequencias de sinais para cobrir todos os casos da tabela verdade 
//Poderia também fazer um full adder com 10 NANDS

full adder/full_adder_test.v
module full_adder_behav_test;
reg a,b, cin;
wire s,c;

full_adder ha1(a,b,cin,s,c);

initial begin
$dumpfile("dumpfile.vcd");
$dumpvars(0, full_adder_behav_test);

a=0; b=0; cin=0;#10;
a=0; b=0; cin=1;#10;
a=0; b=1; cin=0;#10;
a=0; b=1; cin=1;#10;
a=1; b=0; cin=0;#10;
a=1; b=0; cin=1;#10;
a=1; b=1; cin=0;#10;
a=1; b=1; cin=1;#10;

$finish;

end
initial
$monitor("out");
endmodule

full adder/dumpfile.vcd
$date
	Sun Aug 19 20:11:35 2018
$end
$version
	Icarus Verilog
$end
$timescale
	1s
$end
$scope module full_adder_behav_test $end
$var wire 1 ! s $end
$var wire 1 " c $end
$var reg 1 # a $end
$var reg 1 $ b $end
$var reg 1 % cin $end
$scope module ha1 $end
$var wire 1 # a $end
$var wire 1 $ b $end
$var wire 1 % cin $end
$var wire 1 " cout $end
$var wire 1 ! soma $end
$var wire 1 & soma2 $end
$var wire 1 ' soma1 $end
$var wire 1 ( carry2 $end
$var wire 1 ) carry1 $end
$scope module u1 $end
$var wire 1 # a $end
$var wire 1 $ b $end
$var wire 1 ) c $end
$var wire 1 ' s $end
$upscope $end
$scope module u2 $end
$var wire 1 % a $end
$var wire 1 ' b $end
$var wire 1 ( c $end
$var wire 1 & s $end
$upscope $end
$upscope $end
$upscope $end
$enddefinitions $end
#0
$dumpvars
0)
0(
0'
0&
0%
0$
0#
0"
0!
$end
#10
1!
1&
1%
#20
1'
0%
1$
#30
1"
0!
0&
1(
1%
#40
0"
1!
1&
0(
0%
0$
1#
#50
1"
0!
0&
1(
1%
#60
0(
0'
1)
0%
1$
#70
1!
1&
1%
